agent_payments/__init__.py
agent_payments-0.2.0.dist-info/METADATA
agent_payments-0.2.0.dist-info/WHEEL
agent_payments-0.2.0.dist-info/licenses/LICENSE.md
agent_payments-0.2.0.dist-info/RECORD
