Metadata-Version: 2.4
Name: agent-payments
Version: 0.2.0
Summary: Simple infrastructure to enable payments for AI agents
Author-email: Shankar <shankar@neuralpayments.net>
License-File: LICENSE.md
Classifier: License :: OSI Approved :: MIT License
Classifier: Operating System :: OS Independent
Classifier: Programming Language :: Python :: 3
Requires-Python: >=3.7
